antshell/AntShell.py
antshell/__init__.py
antshell/base.py
antshell/dbtools.py
antshell/install.py
antshell/lang.py
antshell/paramikos.py
antshell/release.py
antshell/ssh.py
antshell/sql/init.sql
antshell-0.5.10.data/scripts/a
antshell-0.5.10.data/scripts/antshell
antshell-0.5.10.dist-info/METADATA
antshell-0.5.10.dist-info/RECORD
antshell-0.5.10.dist-info/WHEEL
antshell-0.5.10.dist-info/top_level.txt
