Metadata-Version: 2.1
Name: antshell
Version: 0.5.10
Summary: AntShell Auto SSH
Home-page: http://c.isme.pub/AntShell
Author: Casstiel
Author-email: emo_ooppwwqq0@163.com
License: GPLv3+
Platform: UNKNOWN
Classifier: Development Status :: 5 - Production/Stable
Classifier: Environment :: Console
Classifier: Intended Audience :: Developers
Classifier: Intended Audience :: Information Technology
Classifier: Intended Audience :: System Administrators
Classifier: License :: OSI Approved :: GNU General Public License v3 or later (GPLv3+)
Classifier: Natural Language :: English
Classifier: Operating System :: POSIX
Classifier: Programming Language :: Python :: 2.6
Classifier: Programming Language :: Python :: 2.7
Classifier: Topic :: System :: Installation/Setup
Classifier: Topic :: System :: Systems Administration
Classifier: Topic :: Utilities
Requires-Dist: PyYAML
Requires-Dist: paramiko
Requires-Dist: ansible
Requires-Dist: pyte
Requires-Dist: tqdm
Requires-Dist: gevent
Requires-Dist: setuptools
